[
    {
        "url": "mp.weixin.qq.com/s?__biz=MzU4MTUzMzMyNw==&mid=2247578224&idx=3&sn=2b1ff3939fcb67e42432167068280864",
        "title": "商场如战场！姚振华进厂吃了 “ 闭门羹 ”先撤高管再换安保 “ 中炬 ” 强硬应对",
        "nickname": "令人战栗的腥闻",
        "created_at": "2023-07-25",
        "archive": "gh_010a43ec3ce7_2023-07-25_2247578224_n7MUxkPdzt.y.tar.gz",
        "censored_date": "2023-08-02 07:17:47",
        "censored_msg": "The content has been deleted by the author.",
        "update_date": "2023-08-01 17:09:30"
    },
    {
        "url": "mp.weixin.qq.com/s?__biz=MjM5MjI2NDIzOA==&mid=2796387678&idx=2&sn=35169889d75b62696d0d9c2eec13a4e4",
        "title": "这个百年意大利国民小白鞋帆布鞋！今天竟还不到200块？！",
        "nickname": "钱生钱",
        "created_at": "2023-07-28",
        "archive": "gh_3282d7c3e272_2023-07-28_2796387678_bCsYFEvy35.y.tar.gz",
        "censored_date": "2023-08-02 11:07:53",
        "censored_msg": "The content has been deleted by the author."
    },
    {
        "url": "mp.weixin.qq.com/s?__biz=MjM5MjI2NDIzOA==&mid=2796387717&idx=2&sn=2944b56c57612e873fadd1b7a804d969",
        "title": "为什么中国人用谷物酿酒，而西方人却喜欢用葡萄？？",
        "nickname": "钱生钱",
        "created_at": "2023-07-29",
        "archive": "gh_3282d7c3e272_2023-07-29_2796387717_0tvVYks2rI.y.tar.gz",
        "censored_date": "2023-08-02 11:05:46",
        "censored_msg": "The content has been deleted by the author.",
        "update_date": "2023-08-03 07:39:07"
    },
    {
        "url": "mp.weixin.qq.com/s?__biz=MzA5NTA1ODIwMQ==&mid=2650858660&idx=1&sn=5e9e40ec0d45530030cf2ea3e9626776",
        "title": "黄建波：看海，怎么能不来平潭！",
        "nickname": "观八闽",
        "created_at": "2023-08-02",
        "archive": "gh_cf7f88f0bfe8_2023-08-02_2650858660_6g5NfB30jR.y.tar.gz",
        "censored_date": "2023-08-02 21:48:48",
        "censored_msg": "The content has been deleted by the author."
    },
    {
        "url": "mp.weixin.qq.com/s?__biz=MzIzNDgwMjc5NQ==&mid=2247497829&idx=2&sn=e24f612ee3e8dc7ae771b6366a6eb0ad",
        "title": "加我微信，平时在朋友圈围绕热点进行互动",
        "nickname": "叫虱",
        "created_at": "2023-08-01",
        "archive": "gh_1aa55fadd2a2_2023-08-01_2247497829_8xUIudlSRY.y.tar.gz",
        "censored_date": "2023-08-03 02:14:33",
        "censored_msg": "The content has been deleted by the author.",
        "update_date": "2023-08-02 05:57:37"
    },
    {
        "url": "mp.weixin.qq.com/s?__biz=MzA4NDU4MDQ5Mg==&mid=2654191547&idx=1&sn=f96f7d0d8bbb417157db38332d0c8325",
        "title": "楼市又涨价！北京、广州、深圳群魔乱舞",
        "nickname": "横贯线",
        "created_at": "2023-08-01",
        "archive": "gh_4f4f5995e9e5_2023-08-01_2654191547_uhSrACG8OP.y.tar.gz",
        "censored_date": "2023-08-03 03:29:46",
        "censored_msg": "The content has been deleted by the author.",
        "update_date": "2023-08-02 07:52:55"
    }
]